qscout/__init__.py
qscout/v1/__init__.py
qscout/v1/native_gates.py
qscout/v1/noisy.py
qscout/v1/std/__init__.py
qscout/v1/std/stretched.py
test_QSCOUT_gatemodels-0.0.1.1.0.0rc2.data/data/share/qscout-gatemodels/tests/__init__.py
test_QSCOUT_gatemodels-0.0.1.1.0.0rc2.data/data/share/qscout-gatemodels/tests/parser/__init__.py
test_QSCOUT_gatemodels-0.0.1.1.0.0rc2.data/data/share/qscout-gatemodels/tests/parser/test_jaqalpup_parser.py
test_QSCOUT_gatemodels-0.0.1.1.0.0rc2.dist-info/LICENSE
test_QSCOUT_gatemodels-0.0.1.1.0.0rc2.dist-info/METADATA
test_QSCOUT_gatemodels-0.0.1.1.0.0rc2.dist-info/NOTICE
test_QSCOUT_gatemodels-0.0.1.1.0.0rc2.dist-info/WHEEL
test_QSCOUT_gatemodels-0.0.1.1.0.0rc2.dist-info/top_level.txt
test_QSCOUT_gatemodels-0.0.1.1.0.0rc2.dist-info/RECORD
